mcp_azure_devops/__init__.py
mcp_azure_devops/__main__.py
mcp_azure_devops/server.py
mcp_azure_devops/features/__init__.py
mcp_azure_devops/features/projects/__init__.py
mcp_azure_devops/features/projects/common.py
mcp_azure_devops/features/projects/tools.py
mcp_azure_devops/features/teams/__init__.py
mcp_azure_devops/features/teams/common.py
mcp_azure_devops/features/teams/tools.py
mcp_azure_devops/features/work_items/__init__.py
mcp_azure_devops/features/work_items/common.py
mcp_azure_devops/features/work_items/formatting.py
mcp_azure_devops/features/work_items/tools/__init__.py
mcp_azure_devops/features/work_items/tools/comments.py
mcp_azure_devops/features/work_items/tools/create.py
mcp_azure_devops/features/work_items/tools/process.py
mcp_azure_devops/features/work_items/tools/query.py
mcp_azure_devops/features/work_items/tools/read.py
mcp_azure_devops/features/work_items/tools/templates.py
mcp_azure_devops/features/work_items/tools/types.py
mcp_azure_devops/utils/__init__.py
mcp_azure_devops/utils/azure_client.py
mcp_azure_devops/utils/conventions_promp.py
mcp_azure_devops-0.6.0.dist-info/licenses/LICENSE
mcp_azure_devops-0.6.0.dist-info/METADATA
mcp_azure_devops-0.6.0.dist-info/WHEEL
mcp_azure_devops-0.6.0.dist-info/entry_points.txt
mcp_azure_devops-0.6.0.dist-info/top_level.txt
mcp_azure_devops-0.6.0.dist-info/RECORD
