Metadata-Version: 2.4
Name: mcp-azure-devops
Version: 0.6.0
Summary: A Model Context Protocol (MCP) server for Azure DevOps
Author-email: "Atle H. Havsø" <atle@havso.net>
License: MIT License
Project-URL: Homepage, https://github.com/Vortiago/mcp-azure-devops
Project-URL: Bug Tracker, https://github.com/Vortiago/mcp-azure-devops/issues
Requires-Python: >=3.10
License-File: LICENSE
Requires-Dist: azure-devops>=7.1.0b4
Requires-Dist: mcp>=0.1.0
Provides-Extra: dev
Requires-Dist: mcp[cli]>=0.1.0; extra == "dev"
Requires-Dist: pytest>=7.0.0; extra == "dev"
Requires-Dist: pytest-asyncio>=0.21.0; extra == "dev"
Requires-Dist: ruff>=0.0.267; extra == "dev"
Requires-Dist: anyio>=3.6.2; extra == "dev"
Requires-Dist: pyright>=1.1.350; extra == "dev"
Dynamic: license-file
